odoo/addons/rpc_helper/README.rst
odoo/addons/rpc_helper/__init__.py
odoo/addons/rpc_helper/__manifest__.py
odoo/addons/rpc_helper/decorator.py
odoo/addons/rpc_helper/hooks.py
odoo/addons/rpc_helper/patch.py
odoo/addons/rpc_helper/rpc_test_example.py
odoo/addons/rpc_helper/i18n/es_AR.po
odoo/addons/rpc_helper/i18n/rpc_helper.pot
odoo/addons/rpc_helper/models/__init__.py
odoo/addons/rpc_helper/models/ir_model.py
odoo/addons/rpc_helper/readme/CONFIGURE.rst
odoo/addons/rpc_helper/readme/CONTRIBUTORS.rst
odoo/addons/rpc_helper/readme/DESCRIPTION.rst
odoo/addons/rpc_helper/readme/USAGE.rst
odoo/addons/rpc_helper/static/description/icon.png
odoo/addons/rpc_helper/static/description/index.html
odoo/addons/rpc_helper/tests/__init__.py
odoo/addons/rpc_helper/tests/test_decorator.py
odoo/addons/rpc_helper/tests/test_xmlrpc.py
odoo/addons/rpc_helper/views/ir_model_views.xml
odoo14_addon_rpc_helper-14.0.1.2.0.dist-info/METADATA
odoo14_addon_rpc_helper-14.0.1.2.0.dist-info/WHEEL
odoo14_addon_rpc_helper-14.0.1.2.0.dist-info/top_level.txt
odoo14_addon_rpc_helper-14.0.1.2.0.dist-info/RECORD
